pywikicli/__init__.py
pywikicli/api.py
pywikicli/cli.py
pywikicli/commands/__init__.py
pywikicli/commands/config_command.py
pywikicli/commands/crawl_command.py
pywikicli/commands/get_command.py
pywikicli/commands/put_command.py
pywikicli/config.py
pywikicli/converters.py
pywikicli/interfaces.py
pywikicli-0.1.11.dist-info/LICENSE
pywikicli-0.1.11.dist-info/METADATA
pywikicli-0.1.11.dist-info/WHEEL
pywikicli-0.1.11.dist-info/entry_points.txt
pywikicli-0.1.11.dist-info/RECORD
