Metadata-Version: 2.3
Name: pywikicli
Version: 0.1.11
Summary: A CLI tool to interact with MediaWiki via its API
License: MIT
Keywords: mediawiki,wiki,cli,bot,python
Author: vilosource
Author-email: viloforge@outlook.com
Requires-Python: >=3.10,<4.0
Classifier: Development Status :: 4 - Beta
Classifier: Environment :: Console
Classifier: Intended Audience :: Developers
Classifier: License :: OSI Approved :: MIT License
Classifier: Programming Language :: Python :: 3
Classifier: Programming Language :: Python :: 3.10
Classifier: Programming Language :: Python :: 3.11
Classifier: Programming Language :: Python :: 3.12
Classifier: Programming Language :: Python :: 3.13
Classifier: Topic :: Software Development :: Libraries :: Python Modules
Classifier: Topic :: Utilities
Requires-Dist: PyYAML (>=6.0,<7.0)
Requires-Dist: click (>=8.1.3,<9.0.0)
Requires-Dist: pypandoc (>=1.15,<2.0)
Requires-Dist: requests (>=2.28.0,<3.0.0)
Project-URL: Homepage, https://github.com/vilosource/wikibot
Project-URL: Repository, https://github.com/vilosource/wikibot
